sqlalchemy_doris/__init__.py
sqlalchemy_doris/_version.py
sqlalchemy_doris/datatype.py
sqlalchemy_doris/dialect.py
sqlalchemy_doris-0.2.2.dist-info/LICENSE
sqlalchemy_doris-0.2.2.dist-info/METADATA
sqlalchemy_doris-0.2.2.dist-info/WHEEL
sqlalchemy_doris-0.2.2.dist-info/entry_points.txt
sqlalchemy_doris-0.2.2.dist-info/top_level.txt
sqlalchemy_doris-0.2.2.dist-info/RECORD
