Metadata-Version: 2.1
Name: sqlalchemy-doris
Version: 0.2.2
Summary: Apache Doris dialect for SQLAlchemy
Author-email: actcwlf <actcwlf@qq.com>
License: Apache Software License
Project-URL: Homepage, https://github.com/actcwlf/sqlalchemy-doris
Project-URL: Issues, https://github.com/actcwlf/sqlalchemy-doris/issues
Keywords: Apache Doris,SQLAlchemy
Classifier: Development Status :: 2 - Pre-Alpha
Classifier: Programming Language :: Python :: 3
Requires-Python: >=3.7
License-File: LICENSE
Requires-Dist: sqlalchemy >=1.4
Requires-Dist: sqlalchemy-utils >=0.38.3
Provides-Extra: mysqldb
Requires-Dist: mysqlclient >=2.1.0 ; extra == 'mysqldb'
Provides-Extra: pymysql
Requires-Dist: pymysql ; extra == 'pymysql'
